consul_srv/__init__.py
consul_srv/query.py
consul_srv-0.4.3.dist-info/DESCRIPTION.rst
consul_srv-0.4.3.dist-info/METADATA
consul_srv-0.4.3.dist-info/RECORD
consul_srv-0.4.3.dist-info/WHEEL
consul_srv-0.4.3.dist-info/metadata.json
consul_srv-0.4.3.dist-info/top_level.txt
