Metadata-Version: 2.0
Name: consul-srv
Version: 0.4.3
Summary: Consul SRV convenience module
Home-page: UNKNOWN
Author: Zach Smith
Author-email: zach.smith@makespace.com
License: BSD3
Platform: UNKNOWN
Requires-Dist: dnspython
Requires-Dist: requests
